{
  "standards": [
    {
      "id": "eu_mdr-os-iec-60601-2-18-2009+amd1-2016",
      "number": "IEC 60601-2-18:2009",
      "title": {
        "en": "Medical electrical equipment - Part 2-18: Particular requirements for the basic safety and essential performance of endoscopic equipment",
        "zh": "医用电气设备 - 第2-18部分：内窥镜设备的基本安全和基本性能专用要求"
      },
      "status": "active",
      "source_url": "https://webstore.iec.ch/en/publication/2621",
      "source_verified": "",
      "category": "endoscopy",
      "standard_type": "non_harmonised",
      "scope": "Endoscopic equipment.",
      "applicable_gsprs": [
        "14",
        "14.1"
      ],
      "abstract": "Particular requirements for endoscopic equipment."
    },
    {
      "id": "iso-8600-1-2025",
      "number": "ISO 8600-1:2025",
      "title": {
        "en": "Endoscopes - Medical endoscopes and endotherapy devices - Part 1: General requirements",
        "zh": "内窥镜 - 医用内窥镜和内镜治疗器械 - 第1部分：通用要求"
      },
      "status": "active",
      "applicable_gsprs": [
        "1",
        "3",
        "5"
      ],
      "standard_type": "non_harmonised",
      "source_url": "https://www.iso.org/standard/84216.html",
      "source_verified": "2026-06-27",
      "abstract": "Defines terms and requirements for endoscopes and endotherapy devices used in practice of medicine. Edition 5, replaces ISO 8600-1:2015. Published 2025-03.",
      "scope": "General requirements for medical endoscopes and endotherapy devices."
    },
    {
      "id": "iec-60601-2-2-2017-a1-2023",
      "number": "IEC 60601-2-2:2017+AMD1:2023",
      "title": {
        "en": "Medical electrical equipment - Part 2-2: Particular requirements for the basic safety and essential performance of high frequency surgical equipment and high frequency surgical accessories",
        "zh": "医用电气设备 - 第2-2部分：高频手术设备和高频手术附件的基本安全和基本性能的特殊要求"
      },
      "status": "active",
      "applicable_gsprs": [
        "1",
        "3",
        "5",
        "9",
        "14"
      ],
      "standard_type": "non_harmonised",
      "source_url": "https://webstore.iec.ch/en/publication/83195",
      "source_verified": "2026-06-27",
      "abstract": "Applies to basic safety and essential performance of HF surgical equipment and accessories. Edition 6.1 (consolidated with Amendment 1:2023). Covers electrosurgery, diathermy.",
      "scope": "High frequency (electrosurgical) equipment and accessories.",
      "note": "EN IEC 60601-2-2:2018/A1:2024 published for EU harmonization."
    },
    {
      "id": "iso-16571-2024-endo",
      "number": "ISO 16571:2024",
      "title": {
        "en": "Systems for evacuation of plume generated by medical devices",
        "zh": "医疗器械产生的烟雾排放系统"
      },
      "status": "active",
      "applicable_gsprs": [
        "1",
        "3",
        "5",
        "9"
      ],
      "standard_type": "non_harmonised",
      "source_url": "https://www.iso.org/standard/83065.html",
      "source_verified": "2026-06-27",
      "abstract": "Requirements and guidelines for systems used to evacuate plume generated by medical devices during endoscopic, laparoscopic and open surgical procedures. Edition 2.",
      "scope": "Plume evacuation systems for endoscopic and surgical procedures."
    },
    {
      "id": "iso-8600-3-2019",
      "number": "ISO 8600-3:2019",
      "title": {
        "en": "Endoscopes - Medical endoscopes and endotherapy devices - Part 3: Determination of field of view and direction of view of endoscopes with optics",
        "zh": "内窥镜 - 医用内窥镜和内镜治疗器械 - 第3部分：带光学系统的内窥镜视野和视向的测定"
      },
      "status": "active",
      "applicable_gsprs": [
        "1",
        "3"
      ],
      "standard_type": "non_harmonised",
      "source_url": "https://www.iso.org/standard/65018.html",
      "source_verified": "2026-06-27",
      "abstract": "Specifies test methods for the determination of field of view and direction of view of endoscopes. Edition 4.",
      "scope": "Optical performance testing for medical endoscopes."
    },
    {
      "id": "iso-8600-5-2020",
      "number": "ISO 8600-5:2020",
      "title": {
        "en": "Endoscopes - Medical endoscopes and endotherapy devices - Part 5: Determination of optical resolution of rigid endoscopes with optics",
        "zh": "内窥镜 - 医用内窥镜和内镜治疗器械 - 第5部分：带光学系统的硬式内窥镜光学分辨率的测定"
      },
      "status": "active",
      "applicable_gsprs": [
        "1",
        "3"
      ],
      "standard_type": "non_harmonised",
      "source_url": "https://www.iso.org/standard/65019.html",
      "source_verified": "2026-06-27",
      "abstract": "Specifies methods for the determination of optical resolution of rigid endoscopes. Edition 3.",
      "scope": "Optical resolution testing for rigid endoscopes."
    }
  ]
}
